mcp_server_stats/__init__.py
mcp_server_stats/__main__.py
mcp_server_stats/server.py
mcp_server_stats-0.2.2.dist-info/METADATA
mcp_server_stats-0.2.2.dist-info/WHEEL
mcp_server_stats-0.2.2.dist-info/entry_points.txt
mcp_server_stats-0.2.2.dist-info/top_level.txt
mcp_server_stats-0.2.2.dist-info/RECORD
