Metadata-Version: 2.2
Name: mcp-server-stats
Version: 0.2.2
Summary: A Model Context Protocol server for statistical analysis
Home-page: https://github.com/jamie7893/statsource-mcp
Author: Statsource Team
Author-email: info@statsource.me
Classifier: Programming Language :: Python :: 3
Classifier: License :: OSI Approved :: MIT License
Classifier: Operating System :: OS Independent
Requires-Python: >=3.8
Requires-Dist: mcp<2.0.0,>=1.4.1
Requires-Dist: requests<3.0.0,>=2.31.0
Requires-Dist: pydantic<3.0.0,>=2.4.2
Requires-Dist: python-dotenv<2.0.0,>=1.0.0
Requires-Dist: python-json-logger<3.0.0,>=2.0.7
Dynamic: author
Dynamic: author-email
Dynamic: classifier
Dynamic: description
Dynamic: description-content-type
Dynamic: home-page
Dynamic: requires-dist
Dynamic: requires-python
Dynamic: summary
